{
    "fluentMethods": true,
    "relationships": [
        {
            "relationshipType": "one-to-many",
            "relationshipName": "questionTemplates",
            "otherEntityName": "questionTemplate",
            "otherEntityRelationshipName": "evaluationTemplate"
        },
        {
            "relationshipType": "many-to-one",
            "relationshipValidateRules": "required",
            "relationshipName": "team",
            "otherEntityName": "team",
            "otherEntityField": "id"
        }
    ],
    "fields": [
        {
            "fieldName": "name",
            "fieldType": "String",
            "fieldValidateRules": [
                "required",
                "maxlength"
            ],
            "fieldValidateRulesMaxlength": 30
        },
        {
            "fieldName": "description",
            "fieldType": "String",
            "fieldValidateRules": [
                "maxlength"
            ],
            "fieldValidateRulesMaxlength": 200
        }
    ],
    "changelogDate": "20170510010018",
    "entityTableName": "evaluation_template",
    "dto": "no",
    "pagination": "infinite-scroll",
    "service": "serviceImpl"
}